python_reactive_ui/__init__.py
python_reactive_ui/backends/__init__.py
python_reactive_ui/backends/gtk3/__init__.py
python_reactive_ui/backends/gtk3/builtin/__init__.py
python_reactive_ui/backends/gtk3/builtin/blackbox.py
python_reactive_ui/backends/gtk3/builtin/box.py
python_reactive_ui/backends/gtk3/builtin/button.py
python_reactive_ui/backends/gtk3/builtin/label.py
python_reactive_ui/backends/gtk3/builtin/progress_bar.py
python_reactive_ui/backends/gtk3/builtin/window.py
python_reactive_ui/backends/gtk3/builtin_component.py
python_reactive_ui/backends/gtk3/root.py
python_reactive_ui/example.py
python_reactive_ui/lib/__init__.py
python_reactive_ui/lib/core.py
python_reactive_ui/lib/hooks.py
python_reactive_ui/main.py
python_reactive_ui-0.2.10.dist-info/entry_points.txt
python_reactive_ui-0.2.10.dist-info/WHEEL
python_reactive_ui-0.2.10.dist-info/METADATA
python_reactive_ui-0.2.10.dist-info/RECORD
