Metadata-Version: 2.1
Name: python-reactive-ui
Version: 0.2.10
Summary: 
Author: Manuel Brea
Author-email: m.brea.carreras@gmail.com
Requires-Python: >=3.10,<4.0
Classifier: Programming Language :: Python :: 3
Classifier: Programming Language :: Python :: 3.10
Requires-Dist: PyGObject (>=3.42.2,<4.0.0)
